vending_machine/vending_machine_def.v
// Title         : vending_machine_def.v
// Author      : Jae-Eon Jo (Jojaeeon@postech.ac.kr) 
//					Dongup Kwon (nankdu7@postech.ac.kr)

// Macro constants (prefix k & CamelCase)
`define kTotalBits 32
  
`define kItemBits 8
`define kNumItems 4

`define kCoinBits 8
`define kNumCoins 3

`define kWaitTime 100

vending_machine/change_state.v
`include "vending_machine_def.v"


module change_state(clk,reset_n,current_total_nxt,current_total);

	input clk;
	input reset_n;
	input [`kTotalBits-1:0] current_total_nxt;
	output reg [`kTotalBits-1:0] current_total;
	
	// Sequential circuit to reset or update the states
	always @(posedge clk ) begin
		if (!reset_n) begin
			// TODO: reset all states.
			current_total <=0;
		end
		else begin
			// TODO: update all states.
			current_total <= current_total_nxt;
		end
	end
endmodule

vending_machine/calculate_current_state.v

`include "vending_machine_def.v"
	

module calculate_current_state(i_input_coin,i_select_item,item_price,coin_value,current_total,
input_total, output_total, return_total,current_total_nxt,wait_time,o_return_coin,o_available_item,o_output_item);


	
	input [`kNumCoins-1:0] i_input_coin,o_return_coin;
	input [`kNumItems-1:0]	i_select_item;			
	input [31:0] item_price [`kNumItems-1:0];
	input [31:0] coin_value [`kNumCoins-1:0];	
	input [`kTotalBits-1:0] current_total;
	input [31:0] wait_time;
	output reg [`kNumItems-1:0] o_available_item,o_output_item;
	output reg  [`kTotalBits-1:0] input_total, output_total, return_total,current_total_nxt;
	integer i;	

	
	// Combinational logic for the next states
	always @(*) begin
		// TODO: current_total_nxt
		// You don't have to worry about concurrent activations in each input vector (or array).
		// Calculate the next current_total state.
		
		// Calculate total return coin value
		input_total = 0;
		output_total = 0;
		return_total = 0;

		// Calculate total input coin value
		for (i = 0; i < `kNumCoins; i++) begin
			if (i_input_coin[i]) begin
				input_total += coin_value[i];
			end
		end

		// Calculate total output coin value (for purchasing items)
		for (i = 0; i < `kNumItems; i++) begin 
			if (i_select_item[i] && ((current_total - output_total) >= item_price[i])) begin
				output_total += item_price[i];
			end
		end

		// Calculate total return coin value
		for (i = 0; i < `kNumCoins; i++) begin 
			if (o_return_coin[i]) begin 
				return_total += coin_value[i];
			end
		end

		// Calculate next current_total state
		current_total_nxt = current_total + input_total - output_total - return_total;
	end

	
	
	// Combinational logic for the outputs
	always @(*) begin
		// TODO: o_available_item
		// TODO: o_output_item
		o_available_item = 4'b0000;
		o_output_item = 4'b0000;

		for (i = 0; i < `kNumItems; i++) begin
			if (current_total >= item_price[i]) begin 
				o_available_item[i] = 1;
			end
		end

		for (i = 0; i < `kNumItems; i++) begin
			if (i_select_item[i] && (current_total >= item_price[i])) begin
				o_output_item[i] = 1;
			end
		end 
	end
 
	


endmodule

vending_machine/check_time_and_coin.v
`include "vending_machine_def.v"

	

module check_time_and_coin(i_input_coin,o_output_item,i_trigger_return,clk,reset_n, wait_time,current_total,coin_value,o_return_coin);
	input clk;
	input reset_n;
	input i_trigger_return; //input 추가
	input [`kNumCoins-1:0] i_input_coin;
	// input [`kNumItems-1:0] i_select_item;
	input [`kNumItems-1:0] o_output_item;
	input [`kTotalBits-1:0] current_total; // o_return coin에서 반환해야할 때 자판기에 남은 돈을 전부 리턴해야하므로 current total input에 추가
	input [31:0] coin_value[`kNumCoins-1:0];
	output reg  [`kNumCoins-1:0] o_return_coin;
	output reg [31:0] wait_time;

	// initiate values
	initial begin
		// TODO: initiate values
		o_return_coin = 0;
		wait_time = `kWaitTime; // 시작을 10초로 시작
		coin_value[2], coin_value[1], coin_value[0] =0;
	end


	// // update coin return time
	// always @(i_input_coin, o_output_item, i_trigger_return) begin
	// 	// TODO: update coin return time // 여기 다시 생각해야함
	// 	// if i_input coin exist or i_select_item is 1, update the return time
	// 	if((i_input_coin != 0) || (o_output_item != 0))begin //output item이 있거나, input coin이 들어갔을 때 10초로 다시 갱신
	// 		wait_time = `kWaitTime;
	// 	end
	// 	if(i_trigger_return) begin //triger return 된다면 wait time =0 으로 초기화
	// 		wait_time =0;
	// 	end

	// end

	always @(*) begin
		// TODO: o_return_coin
		o_return_coin = 3'b000;
		if((wait_time == 0 || i_trigger_return) && current_total >0) begin //o_return_coin을 업데이트 해주어야 하는 조건... 수정해야할지도

			if(current_total >= coin_value[2]) begin
				o_return_coin = 3'b100;
			end
			if(current_total - coin_value[2] >= coin_value[1]) begin
				o_return_coin = 3'b010;
			end
			if(current_total - coin_value[2]- coin_value[1] >= coin_value[0]) begin
				o_return_coin = 3'b001;
			end

		end
	end

	always @(posedge clk ) begin
		if (!reset_n) begin
		// TODO: reset all states.
		//처음 initial이랑 똑같이 초기화 시켜줌 post edge에 맞춰서
		wait_time <=`kWaitTime;
		//o_return_coin <= 0;
		end
		if((i_input_coin != 0) || (o_output_item != 0))begin //output item이 있거나, input coin이 들어갔을 때 10초로 다시 갱신
			wait_time <= `kWaitTime;
		end
		else if(i_trigger_return) begin //triger return 된다면 wait time =0 으로 초기화
			wait_time <= 0;
		end
		else begin
			if(wait_time > 0) begin // wait time 0이면 0
				wait_time <= wait_time -1;
			end
		end
	end
endmodule

vending_machine/vending_machine.v
// Title         : vending_machine.v
// Author      : Jae-Eon Jo (Jojaeeon@postech.ac.kr) 
//			     Dongup Kwon (nankdu7@postech.ac.kr) (2015.03.30)
//			     Jaehun Ryu (jaehunryu@postech.ac.kr) (2021.03.07)

`include "vending_machine_def.v"


module vending_machine (
	clk,							// Clock signal
	reset_n,						// Reset signal (active-low)

	i_input_coin,				// coin is inserted.
	i_select_item,				// item is selected.
	i_trigger_return,			// change-return is triggered 

	o_available_item,			// Sign of the item availability
	o_output_item,			// Sign of the item withdrawal
	o_return_coin				// Sign of the coin return
);

	// Ports Declaration
	// Do not modify the module interface
	input clk;
	input reset_n;
	
	input [`kNumCoins-1:0] i_input_coin;
	input [`kNumItems-1:0] i_select_item;
	input i_trigger_return;
		
	output [`kNumItems-1:0] o_available_item;
	output [`kNumItems-1:0] o_output_item;
	output [`kNumCoins-1:0] o_return_coin;


	

	// Do not modify the values.
	wire [31:0] item_price [`kNumItems-1:0];	// Price of each item
	wire [31:0] coin_value [`kNumCoins-1:0];	// Value of each coin
	assign item_price[0] = 400;
	assign item_price[1] = 500;
	assign item_price[2] = 1000;
	assign item_price[3] = 2000;
	assign coin_value[0] = 100;
	assign coin_value[1] = 500;
	assign coin_value[2] = 1000;

	// Internal states. You may add your own net variables.
	wire [`kTotalBits-1:0] current_total;
	
	// Next internal states. You may add your own net variables.
	wire [`kTotalBits-1:0] current_total_nxt;

	
	// Variables. You may add more your own net variables.
	// wire [`kTotalBits-1:0] input_total, output_total, return_total;
	wire [31:0] wait_time;


	// This module interface, structure, and given a number of modules are not mandatory but recommended.
	// However, Implementations that use modules are mandatory.
		
  	check_time_and_coin check_time_and_coin_module(.i_input_coin(i_input_coin),
									.o_output_item(o_output_item),
									.i_trigger_return(i_trigger_return),
									.clk(clk),
									.reset_n(reset_n),
									.wait_time(wait_time),
									.current_total(current_total),
									.coin_value(coin_value),
									.o_return_coin(o_return_coin));

	calculate_current_state calculate_current_state_module(.i_input_coin(i_input_coin),
										.i_select_item(i_select_item),
										.item_price(item_price),
										.coin_value(coin_value),
										.current_total(current_total),
										// .input_total(input_total),
										// .output_total(output_total),
										// .return_total(return_total),
										.current_total_nxt(current_total_nxt),
										.wait_time(wait_time),
										.o_return_coin(o_return_coin),
										.o_available_item(o_available_item),
										.o_output_item(o_output_item));
	
  	change_state change_state_module(
						.clk(clk),
						.reset_n(reset_n),
						.current_total_nxt(current_total_nxt),
						.current_total(current_total));


endmodule

vending_machine/obj_dir/waveform.vcd
$version Generated by VerilatedVcd $end
$timescale 1ps $end
 $scope module TOP $end
  $var wire 1 - clk $end
  $var wire 1 . reset_n $end
  $var wire 3 / i_input_coin [2:0] $end
  $var wire 4 0 i_select_item [3:0] $end
  $var wire 1 1 i_trigger_return $end
  $var wire 4 2 o_available_item [3:0] $end
  $var wire 4 3 o_output_item [3:0] $end
  $var wire 3 4 o_return_coin [2:0] $end
  $scope module vending_machine $end
   $var wire 1 - clk $end
   $var wire 1 . reset_n $end
   $var wire 3 / i_input_coin [2:0] $end
   $var wire 4 0 i_select_item [3:0] $end
   $var wire 1 1 i_trigger_return $end
   $var wire 4 2 o_available_item [3:0] $end
   $var wire 4 3 o_output_item [3:0] $end
   $var wire 3 4 o_return_coin [2:0] $end
   $var wire 32 # item_price[0] [31:0] $end
   $var wire 32 $ item_price[1] [31:0] $end
   $var wire 32 % item_price[2] [31:0] $end
   $var wire 32 & item_price[3] [31:0] $end
   $var wire 32 ' coin_value[0] [31:0] $end
   $var wire 32 ( coin_value[1] [31:0] $end
   $var wire 32 ) coin_value[2] [31:0] $end
   $var wire 32 * current_total [31:0] $end
   $var wire 32 5 current_total_nxt [31:0] $end
   $var wire 32 + wait_time [31:0] $end
   $scope module calculate_current_state_module $end
    $var wire 3 / i_input_coin [2:0] $end
    $var wire 3 4 o_return_coin [2:0] $end
    $var wire 4 0 i_select_item [3:0] $end
    $var wire 32 # item_price[0] [31:0] $end
    $var wire 32 $ item_price[1] [31:0] $end
    $var wire 32 % item_price[2] [31:0] $end
    $var wire 32 & item_price[3] [31:0] $end
    $var wire 32 ' coin_value[0] [31:0] $end
    $var wire 32 ( coin_value[1] [31:0] $end
    $var wire 32 ) coin_value[2] [31:0] $end
    $var wire 32 * current_total [31:0] $end
    $var wire 32 + wait_time [31:0] $end
    $var wire 4 2 o_available_item [3:0] $end
    $var wire 4 3 o_output_item [3:0] $end
    $var wire 32 5 current_total_nxt [31:0] $end
    $var wire 32 , i [31:0] $end
    $var wire 32 6 input_total [31:0] $end
    $var wire 32 7 output_total [31:0] $end
    $var wire 32 8 return_total [31:0] $end
   $upscope $end
   $scope module change_state_module $end
    $var wire 1 - clk $end
    $var wire 1 . reset_n $end
    $var wire 32 5 current_total_nxt [31:0] $end
    $var wire 32 * current_total [31:0] $end
   $upscope $end
   $scope module check_time_and_coin_module $end
    $var wire 1 - clk $end
    $var wire 1 . reset_n $end
    $var wire 1 1 i_trigger_return $end
    $var wire 3 / i_input_coin [2:0] $end
    $var wire 4 3 o_output_item [3:0] $end
    $var wire 32 * current_total [31:0] $end
    $var wire 32 ' coin_value[0] [31:0] $end
    $var wire 32 ( coin_value[1] [31:0] $end
    $var wire 32 ) coin_value[2] [31:0] $end
    $var wire 3 4 o_return_coin [2:0] $end
    $var wire 32 + wait_time [31:0] $end
   $upscope $end
  $upscope $end
 $upscope $end
$enddefinitions $end


#0
b00000000000000000000000110010000 #
b00000000000000000000000111110100 $
b00000000000000000000001111101000 %
b00000000000000000000011111010000 &
b00000000000000000000000001100100 '
b00000000000000000000000111110100 (
b00000000000000000000001111101000 )
b00000000000000000000000000000000 *
b00000000000000000000000000001010 +
b00000000000000000000000000000011 ,
1-
0.
b000 /
b0000 0
01
b0000 2
b0000 3
b000 4
b00000000000000000000000000000000 5
b00000000000000000000000000000000 6
b00000000000000000000000000000000 7
b00000000000000000000000000000000 8
#1
0-
1.
#2
b00000000000000000000000000001001 +
1-
0.
#3
0-
#4
b00000000000000000000000000001000 +
1-
1.
#5
0-
#6
b00000000000000000000000000000111 +
1-
#7
0-
#8
b00000000000000000000000000000110 +
1-
#9
0-
#10
b00000000000000000000000001100100 *
b00000000000000000000000000001010 +
1-
b001 /
b00000000000000000000000011001000 5
b00000000000000000000000001100100 6
#11
0-
b000 /
b00000000000000000000000001100100 5
b00000000000000000000000000000000 6
#12
b00000000000000000000000011001000 *
1-
b001 /
b00000000000000000000000100101100 5
b00000000000000000000000001100100 6
#13
0-
b000 /
b00000000000000000000000011001000 5
b00000000000000000000000000000000 6
#14
b00000000000000000000000100101100 *
1-
b001 /
b00000000000000000000000110010000 5
b00000000000000000000000001100100 6
#15
0-
b000 /
b00000000000000000000000100101100 5
b00000000000000000000000000000000 6
#16
b00000000000000000000000110010000 *
1-
b001 /
b0001 2
b00000000000000000000000111110100 5
b00000000000000000000000001100100 6
#17
0-
b000 /
b00000000000000000000000110010000 5
b00000000000000000000000000000000 6
#18
b00000000000000000000000111110100 *
1-
b001 /
b0011 2
b00000000000000000000001001011000 5
b00000000000000000000000001100100 6
#19
0-
b000 /
b00000000000000000000000111110100 5
b00000000000000000000000000000000 6
#20
b00000000000000000000001001011000 *
1-
b001 /
b00000000000000000000001010111100 5
b00000000000000000000000001100100 6
#21
0-
b000 /
b00000000000000000000001001011000 5
b00000000000000000000000000000000 6
#22
b00000000000000000000001010111100 *
1-
b001 /
b00000000000000000000001100100000 5
b00000000000000000000000001100100 6
#23
0-
b000 /
b00000000000000000000001010111100 5
b00000000000000000000000000000000 6
#24
b00000000000000000000001100100000 *
1-
b001 /
b00000000000000000000001110000100 5
b00000000000000000000000001100100 6
#25
0-
b000 /
b00000000000000000000001100100000 5
b00000000000000000000000000000000 6
#26
b00000000000000000000001110000100 *
1-
b001 /
b00000000000000000000001111101000 5
b00000000000000000000000001100100 6
#27
0-
b000 /
b00000000000000000000001110000100 5
b00000000000000000000000000000000 6
#28
b00000000000000000000001111101000 *
1-
b001 /
b0111 2
b00000000000000000000010001001100 5
b00000000000000000000000001100100 6
#29
0-
b000 /
b00000000000000000000001111101000 5
b00000000000000000000000000000000 6
#30
b00000000000000000000010001001100 *
1-
b001 /
b00000000000000000000010010110000 5
b00000000000000000000000001100100 6
#31
0-
b000 /
b00000000000000000000010001001100 5
b00000000000000000000000000000000 6
#32
b00000000000000000000010010110000 *
1-
b001 /
b00000000000000000000010100010100 5
b00000000000000000000000001100100 6
#33
0-
b000 /
b00000000000000000000010010110000 5
b00000000000000000000000000000000 6
#34
b00000000000000000000010100010100 *
1-
b001 /
b00000000000000000000010101111000 5
b00000000000000000000000001100100 6
#35
0-
b000 /
b00000000000000000000010100010100 5
b00000000000000000000000000000000 6
#36
b00000000000000000000010101111000 *
1-
b001 /
b00000000000000000000010111011100 5
b00000000000000000000000001100100 6
#37
0-
b000 /
b00000000000000000000010101111000 5
b00000000000000000000000000000000 6
#38
b00000000000000000000010111011100 *
1-
b001 /
b00000000000000000000011001000000 5
b00000000000000000000000001100100 6
#39
0-
b000 /
b00000000000000000000010111011100 5
b00000000000000000000000000000000 6
#40
b00000000000000000000011001000000 *
1-
b001 /
b00000000000000000000011010100100 5
b00000000000000000000000001100100 6
#41
0-
b000 /
b00000000000000000000011001000000 5
b00000000000000000000000000000000 6
#42
b00000000000000000000011010100100 *
1-
b001 /
b00000000000000000000011100001000 5
b00000000000000000000000001100100 6
#43
0-
b000 /
b00000000000000000000011010100100 5
b00000000000000000000000000000000 6
#44
b00000000000000000000011100001000 *
1-
b001 /
b00000000000000000000011101101100 5
b00000000000000000000000001100100 6
#45
0-
b000 /
b00000000000000000000011100001000 5
b00000000000000000000000000000000 6
#46
b00000000000000000000011101101100 *
1-
b001 /
b00000000000000000000011111010000 5
b00000000000000000000000001100100 6
#47
0-
b000 /
b00000000000000000000011101101100 5
b00000000000000000000000000000000 6
#48
b00000000000000000000011111010000 *
1-
b001 /
b1111 2
b00000000000000000000100000110100 5
b00000000000000000000000001100100 6
#49
0-
b000 /
b00000000000000000000011111010000 5
b00000000000000000000000000000000 6
#50
b00000000000000000000000000001001 +
1-
#51
0-
#52
b00000000000000000000000000000000 *
b00000000000000000000000000001000 +
1-
0.
b0000 2
b00000000000000000000000000000000 5
#53
0-
1.
b001 /
b00000000000000000000000001100100 5
b00000000000000000000000001100100 6
#54
b00000000000000000000000001100100 *
b00000000000000000000000000001010 +
1-
b00000000000000000000000011001000 5
#55
0-
b000 /
11
b011 4
b11111111111111111111111000001100 5
b00000000000000000000000000000000 6
b00000000000000000000001001011000 8
#56
b11111111111111111111111000001100 *
b00000000000000000000000000000000 +
1-
b1111 2
b111 4
b00000000000000000000000000000000 8
#57
0-
#58
1-
#59
0-
#60
1-
#61
0-
01
#62
b00000000000000000000000000000000 *
b00000000000000000000000000001010 +
1-
0.
b0000 2
b000 4
b00000000000000000000000000000000 5
#63
0-
1.
b010 /
b00000000000000000000000111110100 5
b00000000000000000000000111110100 6
#64
b00000000000000000000000111110100 *
1-
b0011 2
b00000000000000000000001111101000 5
#65
0-
b000 /
11
b011 4
b11111111111111111111111110011100 5
b00000000000000000000000000000000 6
b00000000000000000000001001011000 8
#66
b11111111111111111111111110011100 *
b00000000000000000000000000000000 +
1-
b1111 2
b111 4
b00000000000000000000000000000000 8
#67
0-
#68
1-
#69
0-
#70
1-
#71
0-
01
#72
b00000000000000000000000000000000 *
b00000000000000000000000000001010 +
1-
0.
b0000 2
b000 4
b00000000000000000000000000000000 5
#73
0-
1.
b100 /
b00000000000000000000001111101000 5
b00000000000000000000001111101000 6
#74
b00000000000000000000001111101000 *
1-
b0111 2
b00000000000000000000011111010000 5
#75
0-
b000 /
11
b101 4
b11111111111111111111111110011100 5
b00000000000000000000000000000000 6
b00000000000000000000010001001100 8
#76
b11111111111111111111111110011100 *
b00000000000000000000000000000000 +
1-
b1111 2
b111 4
b00000000000000000000000000000000 8
#77
0-
#78
1-
#79
0-
#80
1-
#81
0-
01
#82
b00000000000000000000000000000000 *
b00000000000000000000000000001010 +
1-
0.
b0000 2
b000 4
b00000000000000000000000000000000 5
#83
0-
1.
b011 /
b00000000000000000000001001011000 5
b00000000000000000000001001011000 6
#84
b00000000000000000000001001011000 *
1-
b0011 2
b00000000000000000000010010110000 5
#85
0-
b000 /
11
b011 4
b00000000000000000000000000000000 5
b00000000000000000000000000000000 6
b00000000000000000000001001011000 8
#86
b00000000000000000000000000000000 *
b00000000000000000000000000000000 +
1-
b0000 2
b000 4
b00000000000000000000000000000000 8
#87
0-
#88
1-
#89
0-
#90
1-
#91
0-
01
#92
b00000000000000000000000000001010 +
1-
0.
#93
0-
1.
b101 /
b00000000000000000000010001001100 5
b00000000000000000000010001001100 6
#94
b00000000000000000000010001001100 *
1-
b0111 2
b00000000000000000000100010011000 5
#95
0-
b000 /
11
b101 4
b00000000000000000000000000000000 5
b00000000000000000000000000000000 6
b00000000000000000000010001001100 8
#96
b00000000000000000000000000000000 *
b00000000000000000000000000000000 +
1-
b0000 2
b000 4
b00000000000000000000000000000000 8
#97
0-
#98
1-
#99
0-
#100
1-
#101
0-
01
#102
b00000000000000000000000000001010 +
1-
0.
#103
0-
1.
b110 /
b00000000000000000000010111011100 5
b00000000000000000000010111011100 6
#104
b00000000000000000000010111011100 *
1-
b0111 2
b00000000000000000000101110111000 5
#105
0-
b000 /
11
b110 4
b00000000000000000000000000000000 5
b00000000000000000000000000000000 6
b00000000000000000000010111011100 8
#106
b00000000000000000000000000000000 *
b00000000000000000000000000000000 +
1-
b0000 2
b000 4
b00000000000000000000000000000000 8
#107
0-
#108
1-
#109
0-
#110
1-
#111
0-
01
#112
b00000000000000000000000000001010 +
1-
0.
#113
0-
1.
b111 /
b00000000000000000000011001000000 5
b00000000000000000000011001000000 6
#114
b00000000000000000000011001000000 *
1-
b0111 2
b00000000000000000000110010000000 5
#115
0-
b000 /
11
b111 4
b00000000000000000000000000000000 5
b00000000000000000000000000000000 6
b00000000000000000000011001000000 8
#116
b00000000000000000000000000000000 *
b00000000000000000000000000000000 +
1-
b0000 2
b000 4
b00000000000000000000000000000000 8
#117
0-
#118
1-
#119
0-
#120
1-
#121
0-
01
#122
b00000000000000000000000000001010 +
1-
0.
#123
0-
1.
b111 /
b00000000000000000000011001000000 5
b00000000000000000000011001000000 6
#124
b00000000000000000000011001000000 *
1-
b0111 2
b00000000000000000000110010000000 5
#125
0-
b000 /
b00000000000000000000011001000000 5
b00000000000000000000000000000000 6
#126
b00000000000000000000000001100100 *
1-
b0110 0
b0000 2
b00000000000000000000000001100100 5
#127
0-
b0000 0
#128
b00000000000000000000000000001001 +
1-
#129
0-
#130
b00000000000000000000000000001000 +
1-
#131
0-
#132
b00000000000000000000000000000111 +
1-
#133
0-
#134
b00000000000000000000000000000110 +
1-
#135
0-
#136
b00000000000000000000000000000101 +
1-
#137
0-
#138
b00000000000000000000000000000100 +
1-
#139
0-
#140
b00000000000000000000000000000011 +
1-
#141
0-
#142
b00000000000000000000000000000010 +
1-
#143
0-
#144
b00000000000000000000000000000001 +
1-
#145
0-
#146
b00000000000000000000000000000000 +
1-
b011 4
