vending_machine/vending_machine_def.v
// Title         : vending_machine_def.v
// Author      : Jae-Eon Jo (Jojaeeon@postech.ac.kr) 
//					Dongup Kwon (nankdu7@postech.ac.kr)

// Macro constants (prefix k & CamelCase)
`define kTotalBits 32
  
`define kItemBits 8
`define kNumItems 4

`define kCoinBits 8
`define kNumCoins 3

`define kWaitTime 100

vending_machine/change_state.v
`include "vending_machine_def.v"


module change_state(clk,reset_n,current_total_nxt,current_total);

	input clk;
	input reset_n;
	input [`kTotalBits-1:0] current_total_nxt;
	output reg [`kTotalBits-1:0] current_total;
	
	// Sequential circuit to reset or update the states
	always @(posedge clk ) begin
		if (!reset_n) begin
			// TODO: reset all states.
			current_total <=0;
		end
		else begin
			// TODO: update all states.
			current_total <= current_total_nxt;
		end
	end
endmodule

vending_machine/calculate_current_state.v

`include "vending_machine_def.v"
	

module calculate_current_state(i_input_coin,i_select_item,item_price,coin_value,current_total,
input_total, output_total, return_total,current_total_nxt,wait_time,o_return_coin,o_available_item,o_output_item);


	
	input [`kNumCoins-1:0] i_input_coin,o_return_coin;
	input [`kNumItems-1:0]	i_select_item;			
	input [31:0] item_price [`kNumItems-1:0];
	input [31:0] coin_value [`kNumCoins-1:0];	
	input [`kTotalBits-1:0] current_total;
	input [31:0] wait_time;
	output reg [`kNumItems-1:0] o_available_item,o_output_item;
	output reg  [`kTotalBits-1:0] input_total, output_total, return_total,current_total_nxt;
	integer i;	

	
	// Combinational logic for the next states
	always @(*) begin
		// TODO: current_total_nxt
		// You don't have to worry about concurrent activations in each input vector (or array).
		// Calculate the next current_total state.
		
		// Calculate total return coin value
		input_total = 0;
		output_total = 0;
		return_total = 0;

		// Calculate total input coin value
		for (i = 0; i < `kNumCoins; i++) begin
			if (i_input_coin[i]) begin
				input_total += coin_value[i];
			end
		end

		// Calculate total output coin value (for purchasing items)
		for (i = 0; i < `kNumItems; i++) begin 
			if (i_select_item[i] && ((current_total - output_total) >= item_price[i])) begin
				output_total += item_price[i];
			end
		end

		// Calculate total return coin value
		for (i = 0; i < `kNumCoins; i++) begin 
			if (o_return_coin[i]) begin 
				return_total += coin_value[i];
			end
		end

		// Calculate next current_total state
		current_total_nxt = current_total + input_total - output_total - return_total;
	end

	
	
	// Combinational logic for the outputs
	always @(*) begin
		// TODO: o_available_item
		// TODO: o_output_item
		o_available_item = 4'b0000;
		o_output_item = 4'b0000;

		for (i = 0; i < `kNumItems; i++) begin
			if (current_total >= item_price[i]) begin 
				o_available_item[i] = 1;
			end
		end

		for (i = 0; i < `kNumItems; i++) begin
			if (i_select_item[i] && (current_total >= item_price[i])) begin
				o_output_item[i] = 1;
			end
		end 
	end
 
	


endmodule

vending_machine/check_time_and_coin.v
`include "vending_machine_def.v"

	

module check_time_and_coin(i_input_coin,o_output_item,i_trigger_return,clk,reset_n, wait_time,current_total,coin_value,o_return_coin);
	input clk;
	input reset_n;
	input i_trigger_return; //input 추가
	input [`kNumCoins-1:0] i_input_coin;
	// input [`kNumItems-1:0] i_select_item;
	input [`kNumItems-1:0] o_output_item;
	input [`kTotalBits-1:0] current_total; // o_return coin에서 반환해야할 때 자판기에 남은 돈을 전부 리턴해야하므로 current total input에 추가
	input [31:0] coin_value[`kNumCoins-1:0];
	output reg  [`kNumCoins-1:0] o_return_coin;
	output reg [31:0] wait_time;

	// initiate values
	initial begin
		// TODO: initiate values
		o_return_coin = 3'b000;
		wait_time = `kWaitTime + 1; // 시작을 10초로 시작
	end

		
	// // update coin return time
	// always @(i_input_coin, o_output_item, i_trigger_return) begin
	// 	// TODO: update coin return time // 여기 다시 생각해야함
	// 	// if i_input coin exist or i_select_item is 1, update the return time
	// 	if((i_input_coin != 0) || (o_output_item != 0))begin //output item이 있거나, input coin이 들어갔을 때 10초로 다시 갱신
	// 		wait_time = `kWaitTime;
	// 	end
	// 	if(i_trigger_return) begin //triger return 된다면 wait time =0 으로 초기화
	// 		wait_time =0;
	// 	end

	// end

	always @(*) begin
		// TODO: o_return_coin
		//o_return_coin = 3'b000;
		if(wait_time == 0 || i_trigger_return) begin //o_return_coin을 업데이트 해주어야 하는 조건
			if (current_total > 0) begin
				$display("wait_time: ", wait_time);
				if(current_total >= coin_value[2]) begin
					o_return_coin[2] = 1'b1;
				end
				else begin o_return_coin[2] = 1'b0; end

				if(current_total - coin_value[2]*o_return_coin[2] >= coin_value[1]) begin
					o_return_coin[1] = 1'b1;
				end
				else begin o_return_coin[1] = 1'b0; end

				if(current_total - coin_value[2]* o_return_coin[2] - coin_value[1] * o_return_coin[1] >= coin_value[0]) begin
					o_return_coin[0] = 1'b1;
				end
				else begin o_return_coin[0] = 1'b0; end
			end 
			else begin
				o_return_coin = 0;
			end
		end
		// $display(o_return_coin);
		// $display(current_total);
		//if (o_return_coin != 0) begin
		//	$display(o_return_coin);
		//end
		 if(wait_time!=0) o_return_coin = 3'b000; // wait time이 0이 아니면 계산을 위해 다시 0으로
		 else o_return_coin = o_return_coin; //wait time 이 0이면 o_return_coin 계산한걸로 리턴
	end

	always @(posedge clk ) begin
		if (!reset_n) begin
		// TODO: reset all states.
		//처음 initial이랑 똑같이 초기화 시켜줌 post edge에 맞춰서
		wait_time <=`kWaitTime + 1;
		//o_return_coin <= 0;
		end
		if((i_input_coin != 0) || (o_output_item != 0))begin //output item이 있거나, input coin이 들어갔을 때 10초로 다시 갱신
			wait_time <= `kWaitTime + 1;
		end
		else if(i_trigger_return) begin //triger return 된다면 wait time =0 으로 초기화
			wait_time <= 3;
			if(wait_time > 0) begin // wait time 0이면 0
				wait_time <= wait_time -1;
			end
		end
		else begin
			if(wait_time > 0) begin // wait time 0이면 0
				wait_time <= wait_time -1;
			end
		end
	end
endmodule

vending_machine/vending_machine.v
// Title         : vending_machine.v
// Author      : Jae-Eon Jo (Jojaeeon@postech.ac.kr) 
//			     Dongup Kwon (nankdu7@postech.ac.kr) (2015.03.30)
//			     Jaehun Ryu (jaehunryu@postech.ac.kr) (2021.03.07)

`include "vending_machine_def.v"


module vending_machine (
	clk,							// Clock signal
	reset_n,						// Reset signal (active-low)

	i_input_coin,				// coin is inserted.
	i_select_item,				// item is selected.
	i_trigger_return,			// change-return is triggered 

	o_available_item,			// Sign of the item availability
	o_output_item,			// Sign of the item withdrawal
	o_return_coin				// Sign of the coin return
);

	// Ports Declaration
	// Do not modify the module interface
	input clk;
	input reset_n;
	
	input [`kNumCoins-1:0] i_input_coin;
	input [`kNumItems-1:0] i_select_item;
	input i_trigger_return;
		
	output [`kNumItems-1:0] o_available_item;
	output [`kNumItems-1:0] o_output_item;
	output [`kNumCoins-1:0] o_return_coin;


	

	// Do not modify the values.
	wire [31:0] item_price [`kNumItems-1:0];	// Price of each item
	wire [31:0] coin_value [`kNumCoins-1:0];	// Value of each coin
	assign item_price[0] = 400;
	assign item_price[1] = 500;
	assign item_price[2] = 1000;
	assign item_price[3] = 2000;
	assign coin_value[0] = 100;
	assign coin_value[1] = 500;
	assign coin_value[2] = 1000;

	// Internal states. You may add your own net variables.
	wire [`kTotalBits-1:0] current_total;
	
	// Next internal states. You may add your own net variables.
	wire [`kTotalBits-1:0] current_total_nxt;

	
	// Variables. You may add more your own net variables.
	// wire [`kTotalBits-1:0] input_total, output_total, return_total;
	wire [31:0] wait_time;


	// This module interface, structure, and given a number of modules are not mandatory but recommended.
	// However, Implementations that use modules are mandatory.
		
  	check_time_and_coin check_time_and_coin_module(.i_input_coin(i_input_coin),
									.o_output_item(o_output_item),
									.i_trigger_return(i_trigger_return),
									.clk(clk),
									.reset_n(reset_n),
									.wait_time(wait_time),
									.current_total(current_total),
									.coin_value(coin_value),
									.o_return_coin(o_return_coin));

	calculate_current_state calculate_current_state_module(.i_input_coin(i_input_coin),
										.i_select_item(i_select_item),
										.item_price(item_price),
										.coin_value(coin_value),
										.current_total(current_total),
										// .input_total(input_total),
										// .output_total(output_total),
										// .return_total(return_total),
										.current_total_nxt(current_total_nxt),
										.wait_time(wait_time),
										.o_return_coin(o_return_coin),
										.o_available_item(o_available_item),
										.o_output_item(o_output_item));
	
  	change_state change_state_module(
						.clk(clk),
						.reset_n(reset_n),
						.current_total_nxt(current_total_nxt),
						.current_total(current_total));


endmodule

vending_machine/waveform.vcd
$version Generated by VerilatedVcd $end
$timescale 1ps $end
 $scope module TOP $end
  $var wire 1 - clk $end
  $var wire 1 . reset_n $end
  $var wire 3 / i_input_coin [2:0] $end
  $var wire 4 0 i_select_item [3:0] $end
  $var wire 1 1 i_trigger_return $end
  $var wire 4 2 o_available_item [3:0] $end
  $var wire 4 3 o_output_item [3:0] $end
  $var wire 3 4 o_return_coin [2:0] $end
  $scope module vending_machine $end
   $var wire 1 - clk $end
   $var wire 1 . reset_n $end
   $var wire 3 / i_input_coin [2:0] $end
   $var wire 4 0 i_select_item [3:0] $end
   $var wire 1 1 i_trigger_return $end
   $var wire 4 2 o_available_item [3:0] $end
   $var wire 4 3 o_output_item [3:0] $end
   $var wire 3 4 o_return_coin [2:0] $end
   $var wire 32 # item_price[0] [31:0] $end
   $var wire 32 $ item_price[1] [31:0] $end
   $var wire 32 % item_price[2] [31:0] $end
   $var wire 32 & item_price[3] [31:0] $end
   $var wire 32 ' coin_value[0] [31:0] $end
   $var wire 32 ( coin_value[1] [31:0] $end
   $var wire 32 ) coin_value[2] [31:0] $end
   $var wire 32 * current_total [31:0] $end
   $var wire 32 5 current_total_nxt [31:0] $end
   $var wire 32 + wait_time [31:0] $end
   $scope module calculate_current_state_module $end
    $var wire 3 / i_input_coin [2:0] $end
    $var wire 3 4 o_return_coin [2:0] $end
    $var wire 4 0 i_select_item [3:0] $end
    $var wire 32 # item_price[0] [31:0] $end
    $var wire 32 $ item_price[1] [31:0] $end
    $var wire 32 % item_price[2] [31:0] $end
    $var wire 32 & item_price[3] [31:0] $end
    $var wire 32 ' coin_value[0] [31:0] $end
    $var wire 32 ( coin_value[1] [31:0] $end
    $var wire 32 ) coin_value[2] [31:0] $end
    $var wire 32 * current_total [31:0] $end
    $var wire 32 + wait_time [31:0] $end
    $var wire 4 2 o_available_item [3:0] $end
    $var wire 4 3 o_output_item [3:0] $end
    $var wire 32 5 current_total_nxt [31:0] $end
    $var wire 32 , i [31:0] $end
    $var wire 32 6 input_total [31:0] $end
    $var wire 32 7 output_total [31:0] $end
    $var wire 32 8 return_total [31:0] $end
   $upscope $end
   $scope module change_state_module $end
    $var wire 1 - clk $end
    $var wire 1 . reset_n $end
    $var wire 32 5 current_total_nxt [31:0] $end
    $var wire 32 * current_total [31:0] $end
   $upscope $end
   $scope module check_time_and_coin_module $end
    $var wire 1 - clk $end
    $var wire 1 . reset_n $end
    $var wire 1 1 i_trigger_return $end
    $var wire 3 / i_input_coin [2:0] $end
    $var wire 4 3 o_output_item [3:0] $end
    $var wire 32 * current_total [31:0] $end
    $var wire 32 ' coin_value[0] [31:0] $end
    $var wire 32 ( coin_value[1] [31:0] $end
    $var wire 32 ) coin_value[2] [31:0] $end
    $var wire 3 4 o_return_coin [2:0] $end
    $var wire 32 + wait_time [31:0] $end
   $upscope $end
  $upscope $end
 $upscope $end
$enddefinitions $end


#0
b00000000000000000000000110010000 #
b00000000000000000000000111110100 $
b00000000000000000000001111101000 %
b00000000000000000000011111010000 &
b00000000000000000000000001100100 '
b00000000000000000000000111110100 (
b00000000000000000000001111101000 )
b11000110010101111110111011101001 *
b00000000000000000000000000001011 +
b00000000000000000000000000000100 ,
1-
1.
b000 /
b0000 0
01
b1111 2
b0000 3
b000 4
b11000110010101111110111011101001 5
b00000000000000000000000000000000 6
b00000000000000000000000000000000 7
b00000000000000000000000000000000 8
#1
0-
#2
b00000000000000000000000000000000 *
b00000000000000000000000000001010 +
1-
0.
b0000 2
b00000000000000000000000000000000 5
#3
0-
#4
b00000000000000000000000000001001 +
1-
#5
0-
#6
b00000000000000000000000000001000 +
1-
1.
#7
0-
#8
b00000000000000000000000001100100 *
b00000000000000000000000000001011 +
1-
b001 /
b00000000000000000000000011001000 5
b00000000000000000000000001100100 6
#9
0-
#10
b00000000000000000000000000001010 +
1-
b000 /
b00000000000000000000000001100100 5
b00000000000000000000000000000000 6
#11
0-
#12
b00000000000000000000000011001000 *
b00000000000000000000000000001011 +
1-
b001 /
b00000000000000000000000100101100 5
b00000000000000000000000001100100 6
#13
0-
#14
b00000000000000000000000000001010 +
1-
b000 /
b00000000000000000000000011001000 5
b00000000000000000000000000000000 6
#15
0-
#16
b00000000000000000000000100101100 *
b00000000000000000000000000001011 +
1-
b001 /
b00000000000000000000000110010000 5
b00000000000000000000000001100100 6
#17
0-
#18
b00000000000000000000000000001010 +
1-
b000 /
b00000000000000000000000100101100 5
b00000000000000000000000000000000 6
#19
0-
#20
b00000000000000000000000110010000 *
b00000000000000000000000000001011 +
1-
b001 /
b0001 2
b00000000000000000000000111110100 5
b00000000000000000000000001100100 6
#21
0-
#22
b00000000000000000000000000001010 +
1-
b000 /
b00000000000000000000000110010000 5
b00000000000000000000000000000000 6
#23
0-
#24
b00000000000000000000000111110100 *
b00000000000000000000000000001011 +
1-
b001 /
b0011 2
b00000000000000000000001001011000 5
b00000000000000000000000001100100 6
#25
0-
#26
b00000000000000000000000000001010 +
1-
b000 /
b00000000000000000000000111110100 5
b00000000000000000000000000000000 6
#27
0-
#28
b00000000000000000000000000001001 +
1-
#29
0-
#30
b00000000000000000000000000000000 *
b00000000000000000000000000001000 +
1-
0.
b0000 2
b00000000000000000000000000000000 5
#31
0-
#32
b00000000000000000000000000000111 +
1-
#33
0-
#34
b00000000000000000000000000000110 +
1-
1.
#35
0-
#36
b00000000000000000000000111110100 *
b00000000000000000000000000001011 +
1-
b010 /
b0011 2
b00000000000000000000001111101000 5
b00000000000000000000000111110100 6
#37
0-
#38
b00000000000000000000000000001010 +
1-
b000 /
b00000000000000000000000111110100 5
b00000000000000000000000000000000 6
#39
0-
#40
b00000000000000000000001111101000 *
b00000000000000000000000000001011 +
1-
b010 /
b0111 2
b00000000000000000000010111011100 5
b00000000000000000000000111110100 6
#41
0-
#42
b00000000000000000000000000001010 +
1-
b000 /
b00000000000000000000001111101000 5
b00000000000000000000000000000000 6
#43
0-
#44
b00000000000000000000010111011100 *
b00000000000000000000000000001011 +
1-
b010 /
b00000000000000000000011111010000 5
b00000000000000000000000111110100 6
#45
0-
#46
b00000000000000000000000000001010 +
1-
b000 /
b00000000000000000000010111011100 5
b00000000000000000000000000000000 6
#47
0-
#48
b00000000000000000000011111010000 *
b00000000000000000000000000001011 +
1-
b010 /
b1111 2
b00000000000000000000100111000100 5
b00000000000000000000000111110100 6
#49
0-
#50
b00000000000000000000000000001010 +
1-
b000 /
b00000000000000000000011111010000 5
b00000000000000000000000000000000 6
#51
0-
#52
b00000000000000000000000000001001 +
1-
#53
0-
#54
b00000000000000000000000000000000 *
b00000000000000000000000000001000 +
1-
0.
b0000 2
b00000000000000000000000000000000 5
#55
0-
#56
b00000000000000000000000000000111 +
1-
#57
0-
#58
b00000000000000000000000000000110 +
1-
1.
#59
0-
#60
b00000000000000000000001111101000 *
b00000000000000000000000000001011 +
1-
b100 /
b0111 2
b00000000000000000000011111010000 5
b00000000000000000000001111101000 6
#61
0-
#62
b00000000000000000000000000001010 +
1-
b000 /
b00000000000000000000001111101000 5
b00000000000000000000000000000000 6
#63
0-
#64
b00000000000000000000011111010000 *
b00000000000000000000000000001011 +
1-
b100 /
b1111 2
b00000000000000000000101110111000 5
b00000000000000000000001111101000 6
#65
0-
#66
b00000000000000000000000000001010 +
1-
b000 /
b00000000000000000000011111010000 5
b00000000000000000000000000000000 6
#67
0-
#68
b00000000000000000000000000001001 +
1-
#69
0-
#70
b00000000000000000000000000000000 *
b00000000000000000000000000001000 +
1-
0.
b0000 2
b00000000000000000000000000000000 5
#71
0-
#72
b00000000000000000000000000000111 +
1-
#73
0-
#74
b00000000000000000000000000000110 +
1-
1.
#75
0-
#76
b00000000000000000000001111101000 *
b00000000000000000000000000001011 +
1-
b100 /
b0111 2
b00000000000000000000011111010000 5
b00000000000000000000001111101000 6
#77
0-
#78
b00000000000000000000000000001010 +
1-
b000 /
b00000000000000000000001111101000 5
b00000000000000000000000000000000 6
#79
0-
#80
b00000000000000000000011111010000 *
b00000000000000000000000000001011 +
1-
b100 /
b1111 2
b00000000000000000000101110111000 5
b00000000000000000000001111101000 6
#81
0-
#82
b00000000000000000000000000001010 +
1-
b000 /
b00000000000000000000011111010000 5
b00000000000000000000000000000000 6
#83
0-
#84
b00000000000000000000101110111000 *
b00000000000000000000000000001011 +
1-
b100 /
b00000000000000000000111110100000 5
b00000000000000000000001111101000 6
#85
0-
#86
b00000000000000000000000000001010 +
1-
b000 /
b00000000000000000000101110111000 5
b00000000000000000000000000000000 6
#87
0-
#88
b00000000000000000000101000101000 *
b00000000000000000000000000001011 +
1-
b0001 0
b0001 3
b00000000000000000000100010011000 5
b00000000000000000000000110010000 7
#89
0-
#90
b00000000000000000000000000001010 +
1-
b0000 0
b0000 3
b00000000000000000000101000101000 5
b00000000000000000000000000000000 7
#91
0-
#92
b00000000000000000000000000001001 +
1-
#93
0-
#94
b00000000000000000000000000001000 +
1-
#95
0-
#96
b00000000000000000000100010011000 *
b00000000000000000000000000001011 +
1-
b0001 0
b0001 3
b00000000000000000000011100001000 5
b00000000000000000000000110010000 7
#97
0-
#98
b00000000000000000000000000001010 +
1-
b0000 0
b0000 3
b00000000000000000000100010011000 5
b00000000000000000000000000000000 7
#99
0-
#100
b00000000000000000000000000001001 +
1-
#101
0-
#102
b00000000000000000000000000001000 +
1-
#103
0-
#104
b00000000000000000000011100001000 *
b00000000000000000000000000001011 +
1-
b0001 0
b0111 2
b0001 3
b00000000000000000000010101111000 5
b00000000000000000000000110010000 7
#105
0-
#106
b00000000000000000000000000001010 +
1-
b0000 0
b0000 3
b00000000000000000000011100001000 5
b00000000000000000000000000000000 7
#107
0-
#108
b00000000000000000000000000001001 +
1-
#109
0-
#110
b00000000000000000000000000001000 +
1-
#111
0-
#112
b00000000000000000000010101111000 *
b00000000000000000000000000001011 +
1-
b0001 0
b0001 3
b00000000000000000000001111101000 5
b00000000000000000000000110010000 7
#113
0-
#114
b00000000000000000000000000001010 +
1-
b0000 0
b0000 3
b00000000000000000000010101111000 5
b00000000000000000000000000000000 7
#115
0-
#116
b00000000000000000000000000001001 +
1-
#117
0-
#118
b00000000000000000000000000001000 +
1-
#119
0-
#120
b00000000000000000000001111101000 *
b00000000000000000000000000001011 +
1-
b0001 0
b0001 3
b00000000000000000000001001011000 5
b00000000000000000000000110010000 7
#121
0-
#122
b00000000000000000000000000001010 +
1-
b0000 0
b0000 3
b00000000000000000000001111101000 5
b00000000000000000000000000000000 7
#123
0-
#124
b00000000000000000000000000001001 +
1-
#125
0-
#126
b00000000000000000000000000001000 +
1-
#127
0-
#128
b00000000000000000000001001011000 *
b00000000000000000000000000001011 +
1-
b0001 0
b0011 2
b0001 3
b00000000000000000000000011001000 5
b00000000000000000000000110010000 7
#129
0-
#130
b00000000000000000000000000001010 +
1-
b0000 0
b0000 3
b00000000000000000000001001011000 5
b00000000000000000000000000000000 7
#131
0-
#132
b00000000000000000000000000001001 +
1-
#133
0-
#134
b00000000000000000000000000001000 +
1-
#135
0-
#136
b00000000000000000000000011001000 *
b00000000000000000000000000001011 +
1-
b0001 0
b0000 2
b00000000000000000000000011001000 5
#137
0-
#138
b00000000000000000000000000001010 +
1-
b0000 0
#139
0-
#140
b00000000000000000000000000001001 +
1-
#141
0-
#142
b00000000000000000000000000001000 +
1-
#143
0-
#144
b00000000000000000000000000000111 +
1-
#145
0-
#146
b00000000000000000000000000000110 +
1-
#147
0-
#148
b00000000000000000000010010110000 *
b00000000000000000000000000001011 +
1-
b100 /
b0111 2
b00000000000000000000100010011000 5
b00000000000000000000001111101000 6
#149
0-
#150
b00000000000000000000000000001010 +
1-
b000 /
b00000000000000000000010010110000 5
b00000000000000000000000000000000 6
#151
0-
#152
b00000000000000000000100010011000 *
b00000000000000000000000000001011 +
1-
b100 /
b1111 2
b00000000000000000000110010000000 5
b00000000000000000000001111101000 6
#153
0-
#154
b00000000000000000000000000001010 +
1-
b000 /
b00000000000000000000100010011000 5
b00000000000000000000000000000000 6
#155
0-
#156
b00000000000000000000110010000000 *
b00000000000000000000000000001011 +
1-
b100 /
b00000000000000000001000001101000 5
b00000000000000000000001111101000 6
#157
0-
#158
b00000000000000000000000000001010 +
1-
b000 /
b00000000000000000000110010000000 5
b00000000000000000000000000000000 6
#159
0-
#160
b00000000000000000000101010001100 *
b00000000000000000000000000001011 +
1-
b0010 0
b0010 3
b00000000000000000000100010011000 5
b00000000000000000000000111110100 7
#161
0-
#162
b00000000000000000000000000001010 +
1-
b0000 0
b0000 3
b00000000000000000000101010001100 5
b00000000000000000000000000000000 7
#163
0-
#164
b00000000000000000000000000001001 +
1-
#165
0-
#166
b00000000000000000000000000001000 +
1-
#167
0-
#168
b00000000000000000000100010011000 *
b00000000000000000000000000001011 +
1-
b0010 0
b0010 3
b00000000000000000000011010100100 5
b00000000000000000000000111110100 7
#169
0-
#170
b00000000000000000000000000001010 +
1-
b0000 0
b0000 3
b00000000000000000000100010011000 5
b00000000000000000000000000000000 7
#171
0-
#172
b00000000000000000000000000001001 +
1-
#173
0-
#174
b00000000000000000000000000001000 +
1-
#175
0-
#176
b00000000000000000000011010100100 *
b00000000000000000000000000001011 +
1-
b0010 0
b0111 2
b0010 3
b00000000000000000000010010110000 5
b00000000000000000000000111110100 7
#177
0-
#178
b00000000000000000000000000001010 +
1-
b0000 0
b0000 3
b00000000000000000000011010100100 5
b00000000000000000000000000000000 7
#179
0-
#180
b00000000000000000000000000001001 +
1-
#181
0-
#182
b00000000000000000000000000001000 +
1-
#183
0-
#184
b00000000000000000000010010110000 *
b00000000000000000000000000001011 +
1-
b0010 0
b0010 3
b00000000000000000000001010111100 5
b00000000000000000000000111110100 7
#185
0-
#186
b00000000000000000000000000001010 +
1-
b0000 0
b0000 3
b00000000000000000000010010110000 5
b00000000000000000000000000000000 7
#187
0-
#188
b00000000000000000000000000001001 +
1-
#189
0-
#190
b00000000000000000000000000001000 +
1-
#191
0-
#192
b00000000000000000000001010111100 *
b00000000000000000000000000001011 +
1-
b0010 0
b0011 2
b0010 3
b00000000000000000000000011001000 5
b00000000000000000000000111110100 7
#193
0-
#194
b00000000000000000000000000001010 +
1-
b0000 0
b0000 3
b00000000000000000000001010111100 5
b00000000000000000000000000000000 7
#195
0-
#196
b00000000000000000000000000001001 +
1-
#197
0-
#198
b00000000000000000000000000001000 +
1-
#199
0-
#200
b00000000000000000000000011001000 *
b00000000000000000000000000001011 +
1-
b0010 0
b0000 2
b00000000000000000000000011001000 5
#201
0-
#202
b00000000000000000000000000001010 +
1-
b0000 0
#203
0-
#204
b00000000000000000000000000001001 +
1-
#205
0-
#206
b00000000000000000000000000001000 +
1-
#207
0-
#208
b00000000000000000000000100101100 *
b00000000000000000000000000001011 +
1-
b001 /
b00000000000000000000000110010000 5
b00000000000000000000000001100100 6
#209
0-
#210
b00000000000000000000000000001010 +
1-
b000 /
b00000000000000000000000100101100 5
b00000000000000000000000000000000 6
#211
0-
#212
b00000000000000000000000110010000 *
b00000000000000000000000000001011 +
1-
b001 /
b0001 2
b00000000000000000000000111110100 5
b00000000000000000000000001100100 6
#213
0-
#214
b00000000000000000000000000001010 +
1-
b000 /
b00000000000000000000000110010000 5
b00000000000000000000000000000000 6
#215
0-
#216
b00000000000000000000010101111000 *
b00000000000000000000000000001011 +
1-
b100 /
b0111 2
b00000000000000000000100101100000 5
b00000000000000000000001111101000 6
#217
0-
#218
b00000000000000000000000000001010 +
1-
b000 /
b00000000000000000000010101111000 5
b00000000000000000000000000000000 6
#219
0-
#220
b00000000000000000000100101100000 *
b00000000000000000000000000001011 +
1-
b100 /
b1111 2
b00000000000000000000110101001000 5
b00000000000000000000001111101000 6
#221
0-
#222
b00000000000000000000000000001010 +
1-
b000 /
b00000000000000000000100101100000 5
b00000000000000000000000000000000 6
#223
0-
#224
b00000000000000000000110101001000 *
b00000000000000000000000000001011 +
1-
b100 /
b00000000000000000001000100110000 5
b00000000000000000000001111101000 6
#225
0-
#226
b00000000000000000000000000001010 +
1-
b000 /
b00000000000000000000110101001000 5
b00000000000000000000000000000000 6
#227
0-
#228
b00000000000000000000100101100000 *
b00000000000000000000000000001011 +
1-
b0100 0
b0100 3
b00000000000000000000010101111000 5
b00000000000000000000001111101000 7
#229
0-
#230
b00000000000000000000000000001010 +
1-
b0000 0
b0000 3
b00000000000000000000100101100000 5
b00000000000000000000000000000000 7
#231
0-
#232
b00000000000000000000000000001001 +
1-
#233
0-
#234
b00000000000000000000000000001000 +
1-
#235
0-
#236
b00000000000000000000010101111000 *
b00000000000000000000000000001011 +
1-
b0100 0
b0111 2
b0100 3
b00000000000000000000000110010000 5
b00000000000000000000001111101000 7
#237
0-
#238
b00000000000000000000000000001010 +
1-
b0000 0
b0000 3
b00000000000000000000010101111000 5
b00000000000000000000000000000000 7
#239
0-
#240
b00000000000000000000000000001001 +
1-
#241
0-
#242
b00000000000000000000000000001000 +
1-
#243
0-
#244
b00000000000000000000000110010000 *
b00000000000000000000000000001011 +
1-
b0100 0
b0001 2
b00000000000000000000000110010000 5
#245
0-
#246
b00000000000000000000000000001010 +
1-
b0000 0
#247
0-
#248
b00000000000000000000000000001001 +
1-
#249
0-
#250
b00000000000000000000000000001000 +
1-
#251
0-
#252
b00000000000000000000010101111000 *
b00000000000000000000000000001011 +
1-
b100 /
b0111 2
b00000000000000000000100101100000 5
b00000000000000000000001111101000 6
#253
0-
#254
b00000000000000000000000000001010 +
1-
b000 /
b00000000000000000000010101111000 5
b00000000000000000000000000000000 6
#255
0-
#256
b00000000000000000000100101100000 *
b00000000000000000000000000001011 +
1-
b100 /
b1111 2
b00000000000000000000110101001000 5
b00000000000000000000001111101000 6
#257
0-
#258
b00000000000000000000000000001010 +
1-
b000 /
b00000000000000000000100101100000 5
b00000000000000000000000000000000 6
#259
0-
#260
b00000000000000000000110101001000 *
b00000000000000000000000000001011 +
1-
b100 /
b00000000000000000001000100110000 5
b00000000000000000000001111101000 6
#261
0-
#262
b00000000000000000000000000001010 +
1-
b000 /
b00000000000000000000110101001000 5
b00000000000000000000000000000000 6
#263
0-
#264
b00000000000000000000010101111000 *
b00000000000000000000000000001011 +
1-
b1000 0
b0111 2
b00000000000000000000010101111000 5
#265
0-
#266
b00000000000000000000000000001010 +
1-
b0000 0
#267
0-
#268
b00000000000000000000000000001001 +
1-
#269
0-
#270
b00000000000000000000000000001000 +
1-
#271
0-
#272
b00000000000000000000100101100000 *
b00000000000000000000000000001011 +
1-
b100 /
b1111 2
b00000000000000000000110101001000 5
b00000000000000000000001111101000 6
#273
0-
#274
b00000000000000000000000000001010 +
1-
b000 /
b00000000000000000000100101100000 5
b00000000000000000000000000000000 6
#275
0-
#276
b00000000000000000000000110010000 *
b00000000000000000000000000001011 +
1-
b1000 0
b0001 2
b00000000000000000000000110010000 5
#277
0-
#278
b00000000000000000000000000001010 +
1-
b0000 0
#279
0-
#280
b00000000000000000000000000001001 +
1-
#281
0-
#282
b00000000000000000000000000001000 +
1-
#283
0-
#284
b00000000000000000000000111110100 *
b00000000000000000000000000001011 +
1-
b001 /
b0011 2
b00000000000000000000001001011000 5
b00000000000000000000000001100100 6
#285
0-
#286
b00000000000000000000000000001010 +
1-
b000 /
b00000000000000000000000111110100 5
b00000000000000000000000000000000 6
#287
0-
#288
b00000000000000000000001001011000 *
b00000000000000000000000000001011 +
1-
b001 /
b00000000000000000000001010111100 5
b00000000000000000000000001100100 6
#289
0-
#290
b00000000000000000000000000001010 +
1-
b000 /
b00000000000000000000001001011000 5
b00000000000000000000000000000000 6
#291
0-
#292
b00000000000000000000001010111100 *
b00000000000000000000000000001011 +
1-
b001 /
b00000000000000000000001100100000 5
b00000000000000000000000001100100 6
#293
0-
#294
b00000000000000000000000000001010 +
1-
b000 /
b00000000000000000000001010111100 5
b00000000000000000000000000000000 6
#295
0-
#296
b00000000000000000000001100100000 *
b00000000000000000000000000001011 +
1-
b001 /
b00000000000000000000001110000100 5
b00000000000000000000000001100100 6
#297
0-
#298
b00000000000000000000000000001010 +
1-
b000 /
b00000000000000000000001100100000 5
b00000000000000000000000000000000 6
#299
0-
#300
b00000000000000000000010100010100 *
b00000000000000000000000000001011 +
1-
b010 /
b0111 2
b00000000000000000000011100001000 5
b00000000000000000000000111110100 6
#301
0-
#302
b00000000000000000000000000001010 +
1-
b000 /
b00000000000000000000010100010100 5
b00000000000000000000000000000000 6
#303
0-
#304
b00000000000000000000011100001000 *
b00000000000000000000000000001011 +
1-
b010 /
b00000000000000000000100011111100 5
b00000000000000000000000111110100 6
#305
0-
#306
b00000000000000000000000000001010 +
1-
b000 /
b00000000000000000000011100001000 5
b00000000000000000000000000000000 6
#307
0-
#308
b00000000000000000000101011110000 *
b00000000000000000000000000001011 +
1-
b100 /
b1111 2
b00000000000000000000111011011000 5
b00000000000000000000001111101000 6
#309
0-
#310
b00000000000000000000000000001010 +
1-
b000 /
b00000000000000000000101011110000 5
b00000000000000000000000000000000 6
#311
0-
#312
b00000000000000000000000000001001 +
1-
#313
0-
#314
b00000000000000000000000000001000 +
1-
#315
0-
#316
b00000000000000000000000000000111 +
1-
#317
0-
#318
b00000000000000000000000000000110 +
1-
#319
0-
#320
b00000000000000000000000000000101 +
1-
#321
0-
#322
b00000000000000000000000000000100 +
1-
#323
0-
#324
b00000000000000000000000000000011 +
1-
#325
0-
#326
b00000000000000000000000000000010 +
1-
#327
0-
#328
b00000000000000000000000000000001 +
1-
#329
0-
#330
b00000000000000000000000000000000 +
1-
b0000 2
b111 4
b00000000000000000000010010110000 5
b00000000000000000000011001000000 8
